ttgLib/TextToGcode.py
ttgLib/__init__.py
TextToGcode-1.2.0.dist-info/LICENSE
TextToGcode-1.2.0.dist-info/METADATA
TextToGcode-1.2.0.dist-info/WHEEL
TextToGcode-1.2.0.dist-info/top_level.txt
TextToGcode-1.2.0.dist-info/RECORD
