Metadata-Version: 2.1
Name: TextToGcode
Version: 1.2.0
Summary: Convert strings to gcode commands.
Home-page: https://github.com/Yoyolick/TextToGcode
Author: Ryan Zmuda
Author-email: ryanzmuda@gmail.com
License: UNKNOWN
Platform: UNKNOWN
Classifier: Programming Language :: Python :: 3
Classifier: License :: OSI Approved :: MIT License
Classifier: Operating System :: OS Independent
Requires-Python: >=3.6
